[
    {
        "name": "budgets",
        "type": "array",
        "description": "List of budgets to process",
        "items": {
            "type": "object",
            "required": ["spreadsheet_id", "sheet_gid", "description"],
            "properties": {
                "spreadsheet_id": {
                    "type": "string",
                    "description": "Google Sheets spreadsheet ID"
                },
                "sheet_gid": {
                    "type": "string",
                    "description": "GID of the sheet within spreadsheet"
                },
                "description": {
                    "type": "string",
                    "description": "Human-readable description of this budget"
                },
                "version_notes": {
                    "type": "string",
                    "description": "Optional notes about this version"
                }
            }
        }
    }
] 